perun/proxy/utils/__init__.py
perun/proxy/utils/metadata_expiration.py
perun/proxy/utils/oracle2postgresql.py
perun/proxy/utils/print_docker_versions.py
perun/proxy/utils/run_probes.py
perun/proxy/utils/run_probes_jpmu_test.py
perun/proxy/utils/run_version_script.py
perun/proxy/utils/separate_oidc_logs.py
perun/proxy/utils/separate_ssp_logs.py
perun/proxy/utils/sync_usable_token_types.py
perun/proxy/utils/nagios/__init__.py
perun/proxy/utils/nagios/check_custom_command.py
perun/proxy/utils/nagios/check_dockers.py
perun/proxy/utils/nagios/check_exabgp_propagation.py
perun/proxy/utils/nagios/check_ldap.py
perun/proxy/utils/nagios/check_ldap_syncrepl.py
perun/proxy/utils/nagios/check_mongodb.py
perun/proxy/utils/nagios/check_nginx.py
perun/proxy/utils/nagios/check_oidc_login.py
perun/proxy/utils/nagios/check_pgsql.py
perun/proxy/utils/nagios/check_php_syntax.py
perun/proxy/utils/nagios/check_privacyidea.py
perun/proxy/utils/nagios/check_rpc_status.py
perun/proxy/utils/nagios/check_saml.py
perun/proxy/utils/nagios/check_user_logins.py
perun/proxy/utils/nagios/webserver_availability.py
perun_proxy_utils-3.1.1.dist-info/LICENSE
perun_proxy_utils-3.1.1.dist-info/METADATA
perun_proxy_utils-3.1.1.dist-info/WHEEL
perun_proxy_utils-3.1.1.dist-info/entry_points.txt
perun_proxy_utils-3.1.1.dist-info/top_level.txt
perun_proxy_utils-3.1.1.dist-info/RECORD
