Metadata-Version: 2.1
Name: perun-proxy-utils
Version: 3.1.1
Summary: Utilities and monitoring probes for Perun ProxyIdP
Home-page: https://gitlab.ics.muni.cz/perun/perun-proxyidp/perun-proxy-utils.git
Requires-Python: >=3.9
License-File: LICENSE
Requires-Dist: setuptools
Requires-Dist: pymongo~=4.3
Requires-Dist: asyncssh~=2.13
Requires-Dist: docker~=7.1
Requires-Dist: beautifulsoup4~=4.12
Requires-Dist: requests~=2.31
Requires-Dist: PyYAML<7.0,>=5.4
Requires-Dist: check-nginx-status~=1.0
Requires-Dist: pyotp~=2.9
Requires-Dist: perun.connector~=3.8
Requires-Dist: privacyidea~=3.9
Requires-Dist: flask~=1.1
Requires-Dist: idpyoidc~=2.1
Requires-Dist: sqlalchemy~=1.4
Provides-Extra: ldap
Requires-Dist: ldap3~=2.9.1; extra == "ldap"
Requires-Dist: check-syncrepl-extended~=2020.13; extra == "ldap"
Provides-Extra: oracle
Requires-Dist: cx-Oracle~=8.3; extra == "oracle"
Provides-Extra: postgresql
Requires-Dist: psycopg2-binary~=2.9; extra == "postgresql"
